Metadata-Version: 1.0
Name: pkg-distributions
Version: 0.2
Summary: Gaussian and Binomial distributions
Home-page: UNKNOWN
Author: Rafaela Sousa
Author-email: rafaelaprm@gmail.com
License: UNKNOWN
Platform: UNKNOWN
